sphinx_scylladb_theme/404.html
sphinx_scylladb_theme/__init__.py
sphinx_scylladb_theme/_version.py
sphinx_scylladb_theme/breadcrumbs.html
sphinx_scylladb_theme/content-navigation.html
sphinx_scylladb_theme/contribute.html
sphinx_scylladb_theme/extensions/__init__.py
sphinx_scylladb_theme/extensions/alerts.py
sphinx_scylladb_theme/extensions/grid.py
sphinx_scylladb_theme/extensions/hero_box.py
sphinx_scylladb_theme/extensions/include_tooltip.py
sphinx_scylladb_theme/extensions/labels.py
sphinx_scylladb_theme/extensions/multiversion.py
sphinx_scylladb_theme/extensions/navigation.py
sphinx_scylladb_theme/extensions/panel_box.py
sphinx_scylladb_theme/extensions/topic_box.py
sphinx_scylladb_theme/extensions/utils.py
sphinx_scylladb_theme/extensions/validations.py
sphinx_scylladb_theme/feedback.html
sphinx_scylladb_theme/footer.html
sphinx_scylladb_theme/header.html
sphinx_scylladb_theme/layout.html
sphinx_scylladb_theme/lexers/__init__.py
sphinx_scylladb_theme/lexers/cql.py
sphinx_scylladb_theme/lexers/ditaa.py
sphinx_scylladb_theme/local-scripts.html
sphinx_scylladb_theme/notice.html
sphinx_scylladb_theme/promo-banner.html
sphinx_scylladb_theme/scylladb-scripts.html
sphinx_scylladb_theme/secondary-side-nav.html
sphinx_scylladb_theme/side-nav-toggle.html
sphinx_scylladb_theme/side-nav.html
sphinx_scylladb_theme/static/css/main.css
sphinx_scylladb_theme/static/img/.gitkeep
sphinx_scylladb_theme/static/img/banner-background.svg
sphinx_scylladb_theme/static/img/favicon-228x228.png
sphinx_scylladb_theme/static/img/favicon-32x32.png
sphinx_scylladb_theme/static/img/favicon.ico
sphinx_scylladb_theme/static/img/logo-scylla-horizontal-color.svg
sphinx_scylladb_theme/static/img/logo-scylla-horizontal-light.svg
sphinx_scylladb_theme/static/img/mascots/404.jpg
sphinx_scylladb_theme/static/img/mascots/scylla-3monsters.png
sphinx_scylladb_theme/static/img/mascots/scylla-advisor-crystal.png
sphinx_scylladb_theme/static/img/mascots/scylla-alternator.svg
sphinx_scylladb_theme-1.8.10.dist-info/METADATA
sphinx_scylladb_theme-1.8.10.dist-info/WHEEL
sphinx_scylladb_theme-1.8.10.dist-info/licenses/LICENSE
sphinx_scylladb_theme-1.8.10.dist-info/RECORD
