Metadata-Version: 2.4
Name: sphinx-scylladb-theme
Version: 1.8.10
Summary: A Sphinx Theme for ScyllaDB documentation projects
License-File: LICENSE
Author: David García
Author-email: david@techdocs.studio
Requires-Python: >=3.10,<4.0
Classifier: Programming Language :: Python :: 3
Classifier: Programming Language :: Python :: 3.10
Classifier: Programming Language :: Python :: 3.11
Classifier: Programming Language :: Python :: 3.12
Classifier: Programming Language :: Python :: 3.13
Classifier: Programming Language :: Python :: 3.14
Requires-Dist: Sphinx-Substitution-Extensions (>=2022.2.16,<2026.0.0)
Requires-Dist: beautifulsoup4 (>=4.12.3,<5.0.0)
Requires-Dist: pyyaml (>=6.0.1,<7.0.0)
Requires-Dist: setuptools (>=70.1.1,<81.0.0)
Requires-Dist: sphinx-collapse (>=0.1.1,<0.2.0)
Requires-Dist: sphinx-copybutton (>=0.5.2,<0.6.0)
Requires-Dist: sphinx-notfound-page (>=1.0.4,<2.0.0)
Requires-Dist: sphinx-tabs (>=3.4.5,<4.0.0)
Requires-Dist: sphinxcontrib-mermaid (>=1.0.0,<2.0.0)
